py_chromedriver_autoinstaller/__init__.py
py_chromedriver_autoinstaller/utils.py
py_chromedriver_autoinstaller-1.0.1.dist-info/licenses/LICENSE
py_chromedriver_autoinstaller-1.0.1.dist-info/METADATA
py_chromedriver_autoinstaller-1.0.1.dist-info/WHEEL
py_chromedriver_autoinstaller-1.0.1.dist-info/entry_points.txt
py_chromedriver_autoinstaller-1.0.1.dist-info/top_level.txt
py_chromedriver_autoinstaller-1.0.1.dist-info/RECORD
